{
  "main": {
    "id": "431dcb1dfb247b46",
    "type": "split",
    "children": [
      {
        "id": "6f26aef186b7d49b",
        "type": "split",
        "children": [
          {
            "id": "c6762bbdad75d087",
            "type": "split",
            "dimension": 43.911174785100286,
            "children": [
              {
                "id": "130dfb410a3076e4",
                "type": "tabs",
                "dimension": 66.92307692307692,
                "children": [
                  {
                    "id": "a09837c42b67f2a9",
                    "type": "leaf",
                    "state": {
                      "type": "diff-view",
                      "state": {
                        "file": "Meta/Ideias para Sessão 4.md",
                        "staged": false
                      }
                    }
                  }
                ]
              },
              {
                "id": "be71c752b41345c6",
                "type": "tabs",
                "dimension": 33.07692307692307,
                "children": [
                  {
                    "id": "f4100da6bed96632",
                    "type": "leaf",
                    "state": {
                      "type": "localgraph",
                      "state": {
                        "options": {
                          "collapse-filter": true,
                          "search": "",
                          "localJumps": 1,
                          "localBacklinks": true,
                          "localForelinks": true,
                          "localInterlinks": true,
                          "showTags": false,
                          "showAttachments": true,
                          "hideUnresolved": false,
                          "collapse-color-groups": true,
                          "colorGroups": [
                            {
                              "query": "path:Personagens/  ",
                              "color": {
                                "a": 1,
                                "rgb": 14701138
                              }
                            },
                            {
                              "query": "path:Narrativa/",
                              "color": {
                                "a": 1,
                                "rgb": 14725458
                              }
                            },
                            {
                              "query": "path:Meta/ ",
                              "color": {
                                "a": 1,
                                "rgb": 11657298
                              }
                            },
                            {
                              "query": "path:Cidade/ ",
                              "color": {
                                "a": 1,
                                "rgb": 5431473
                              }
                            }
                          ],
                          "collapse-display": true,
                          "showArrow": true,
                          "textFadeMultiplier": -1.5,
                          "nodeSizeMultiplier": 1.80989583333333,
                          "lineSizeMultiplier": 1.784375,
                          "collapse-forces": true,
                          "centerStrength": 1,
                          "repelStrength": 10,
                          "linkStrength": 1,
                          "linkDistance": 250,
                          "scale": 0.7514342322277584,
                          "close": true
                        }
                      }
                    }
                  }
                ]
              }
            ],
            "direction": "horizontal"
          },
          {
            "id": "dc0266e3248dffc2",
            "type": "tabs",
            "dimension": 56.08882521489972,
            "children": [
              {
                "id": "df535251bc7a0efb",
                "type": "leaf",
                "state": {
                  "type": "markdown",
                  "state": {
                    "file": "Meta/Ideias para Sessão 4.md",
                    "mode": "source",
                    "source": false
                  }
                }
              },
              {
                "id": "9bfaab078cd95e27",
                "type": "leaf",
                "state": {
                  "type": "markdown",
                  "state": {
                    "file": "Ideias para sessão 5.md",
                    "mode": "source",
                    "source": false
                  }
                }
              }
            ],
            "currentTab": 1
          }
        ],
        "direction": "vertical"
      }
    ],
    "direction": "vertical"
  },
  "left": {
    "id": "649082de5508f2bd",
    "type": "split",
    "children": [
      {
        "id": "3c7b9e490366d80b",
        "type": "tabs",
        "children": [
          {
            "id": "b13887fb6b8f23ce",
            "type": "leaf",
            "state": {
              "type": "file-explorer",
              "state": {
                "sortOrder": "alphabetical"
              }
            }
          },
          {
            "id": "6531008e45674e64",
            "type": "leaf",
            "state": {
              "type": "search",
              "state": {
                "query": "",
                "matchingCase": false,
                "explainSearch": false,
                "collapseAll": true,
                "extraContext": false,
                "sortOrder": "alphabetical"
              }
            }
          },
          {
            "id": "3e8491eecb544cdb",
            "type": "leaf",
            "state": {
              "type": "bookmarks",
              "state": {}
            }
          }
        ]
      }
    ],
    "direction": "horizontal",
    "width": 231.5
  },
  "right": {
    "id": "e6a2322448595f37",
    "type": "split",
    "children": [
      {
        "id": "d31685be1dbefb10",
        "type": "tabs",
        "children": [
          {
            "id": "b0e42a952b3d9d0d",
            "type": "leaf",
            "state": {
              "type": "backlink",
              "state": {
                "collapseAll": false,
                "extraContext": false,
                "sortOrder": "alphabetical",
                "showSearch": false,
                "searchQuery": "",
                "backlinkCollapsed": false,
                "unlinkedCollapsed": true
              }
            }
          },
          {
            "id": "6170c774db787567",
            "type": "leaf",
            "state": {
              "type": "outgoing-link",
              "state": {
                "linksCollapsed": false,
                "unlinkedCollapsed": true
              }
            }
          },
          {
            "id": "72554b0f2c16d907",
            "type": "leaf",
            "state": {
              "type": "tag",
              "state": {
                "sortOrder": "frequency",
                "useHierarchy": true
              }
            }
          },
          {
            "id": "f3a1d9c8320c954f",
            "type": "leaf",
            "state": {
              "type": "outline",
              "state": {}
            }
          },
          {
            "id": "05f2b7c93cb278a6",
            "type": "leaf",
            "state": {
              "type": "git-view",
              "state": {}
            }
          }
        ],
        "currentTab": 4
      }
    ],
    "direction": "horizontal",
    "width": 248.5
  },
  "left-ribbon": {
    "hiddenItems": {
      "switcher:Open quick switcher": false,
      "graph:Open graph view": false,
      "canvas:Create new canvas": false,
      "daily-notes:Open today's daily note": false,
      "templates:Insert template": false,
      "command-palette:Open command palette": false,
      "audio-recorder:Start/stop recording": false
    }
  },
  "active": "05f2b7c93cb278a6",
  "lastOpenFiles": [
    "Personagens/Evelyn Whitman.md",
    "Ideias para sessão 5.md",
    "Narrativa/O Culto.md",
    "Meta/Ideias, Plot twists, personagens, eventos inesperados.md",
    "Meta/Ideias para Sessão 4.md",
    "Personagens/Personagens.md",
    "Personagens/Elias Hawthorn.md",
    "Personagens/Henry Holloway.md",
    "Meta/Prompt.md",
    "Meta/Ideias para sessão 2.md",
    "Meta/Meta.md",
    "Meta/TODO.md",
    "Narrativa/A Faminta.md",
    "Cidade/Biblioteca Municipal.md",
    "Cidade/A Floresta Eterna.md",
    "Cidade/Mídia/Vale da Serenidade - O Encanto da Floresta Eterna.md",
    "Cidade/Mídia/Matérias sobre Vale da Serenidade.md",
    "Narrativa/Enterro de Henry Holloway.md",
    "Narrativa/O Ídolo da Penúria.md",
    "Personagens/Benjamin Thornton.md",
    "Cidade/Refúgio das Ervas.md",
    "Cidade/Vale da Serenidade.md",
    "Cidade/Igreja de São Sereno.md",
    "Narrativa/Carta para os jogadores - Benjamin.md",
    "Cidade/Creche Arco-Íris Encantado.md",
    "Personagens/Emily Winchester.md",
    "Assets/carta para albert.png",
    "Canvas.canvas",
    "Untitled 1.canvas",
    "Untitled.canvas",
    "Recording 20231107002617.webm",
    "Recording 20231107002628.webm",
    "Cidade/Mídia",
    "Personagens",
    "Narrativa",
    "Meta/Desafios",
    "Meta/Arcos",
    "Meta",
    "Cidade",
    "Assets/Simbolo na lápide.jpeg",
    "Assets/output.jpg",
    "Assets"
  ]
}